rtox/__init__.py
rtox/__main__.py
rtox/rtox.py
rtox/untox.py
rtox/fabric/__init__.py
rtox/fabric/__main__.py
rtox/fabric/api.py
rtox/fabric/auth.py
rtox/fabric/colors.py
rtox/fabric/context_managers.py
rtox/fabric/decorators.py
rtox/fabric/docs.py
rtox/fabric/exceptions.py
rtox/fabric/io.py
rtox/fabric/job_queue.py
rtox/fabric/main.py
rtox/fabric/network.py
rtox/fabric/operations.py
rtox/fabric/sftp.py
rtox/fabric/state.py
rtox/fabric/task_utils.py
rtox/fabric/tasks.py
rtox/fabric/thread_handling.py
rtox/fabric/utils.py
rtox/fabric/version.py
rtox/fabric/contrib/__init__.py
rtox/fabric/contrib/console.py
rtox/fabric/contrib/django.py
rtox/fabric/contrib/files.py
rtox/fabric/contrib/project.py
rtox-1.0.2.dist-info/METADATA
rtox-1.0.2.dist-info/RECORD
rtox-1.0.2.dist-info/WHEEL
rtox-1.0.2.dist-info/entry_points.txt
rtox-1.0.2.dist-info/pbr.json
rtox-1.0.2.dist-info/top_level.txt
