Metadata-Version: 2.1
Name: rtox
Version: 1.0.2
Summary: Remote tox test runner
Home-page: http://github.com/pycontribs/rtox
Author: Dolph Mathews
Author-email: dolph.mathews@gmail.com
License: Apache-2
Project-URL: Bug Tracker, https://github.com/pycontribs/rtox/issues
Project-URL: Documentation, https://github.com/pycontribs/rtox/blob/master/README.rst
Project-URL: Source Code, https://github.com/pycontribs/rtox.git
Keywords: tox
Requires-Dist: pbr
Requires-Dist: python-gssapi
Requires-Dist: paramiko
